pyKaraoke/__init__.py
pyKaraoke/pyKaraoke.py
pyKaraoke/script.py
pyKaraoke/song.j2
pykaraoke-1.0.10.dist-info/entry_points.txt
pykaraoke-1.0.10.dist-info/LICENSE
pykaraoke-1.0.10.dist-info/WHEEL
pykaraoke-1.0.10.dist-info/METADATA
pykaraoke-1.0.10.dist-info/RECORD
