Metadata-Version: 2.1
Name: pykaraoke
Version: 1.0.10
Summary: A bot that uses the musixmatch API to transform songs into Google Text-to-Speech
Author: John Capobianco
Author-email: ptcapo@gmail.com
Requires-Python: >=3.8,<4.0
Classifier: Programming Language :: Python :: 3
Classifier: Programming Language :: Python :: 3.10
Classifier: Programming Language :: Python :: 3.8
Classifier: Programming Language :: Python :: 3.9
Requires-Dist: Jinja2 (>=3.1.2,<4.0.0)
Requires-Dist: gTTS (>=2.2.4,<3.0.0)
Requires-Dist: pymusixmatch (>=0.3,<0.4)
Requires-Dist: rich (>=12.4.1,<13.0.0)
Requires-Dist: rich-click (>=1.3.0,<2.0.0)
